pyxenon-2.3.1.data/data/bin/xenon-grpc
pyxenon-2.3.1.data/data/lib/xenon-grpc-2.3.0-all.jar
xenon/__init__.py
xenon/compat.py
xenon/create_keys.py
xenon/exceptions.py
xenon/objects.py
xenon/oop.py
xenon/server.py
xenon/version.py
xenon/proto/__init__.py
xenon/proto/xenon_pb2.py
xenon/proto/xenon_pb2_grpc.py
pyxenon-2.3.1.dist-info/LICENSE
pyxenon-2.3.1.dist-info/METADATA
pyxenon-2.3.1.dist-info/NOTICE
pyxenon-2.3.1.dist-info/WHEEL
pyxenon-2.3.1.dist-info/top_level.txt
pyxenon-2.3.1.dist-info/RECORD
