Metadata-Version: 2.1
Name: pyxenon
Version: 2.3.1
Summary: Python wrapper for the Xenon API.
Home-page: https://github.com/NLeSC/pyxenon
Author: Johan Hidding
Author-email: j.hididng@esciencecenter.nl
License: UNKNOWN
Platform: UNKNOWN
Classifier: License :: OSI Approved :: Apache Software License
Classifier: Intended Audience :: Developers
Classifier: Intended Audience :: Science/Research
Classifier: Environment :: Console
Classifier: Development Status :: 4 - Beta
Classifier: Programming Language :: Python :: 3.4
Classifier: Programming Language :: Python :: 3.5
Classifier: Programming Language :: Python :: 3.6
Classifier: Topic :: System :: Distributed Computing
Requires-Dist: grpcio
Requires-Dist: grpcio-tools
Requires-Dist: pyxdg
Requires-Dist: pyopenssl
Provides-Extra: develop
Requires-Dist: sphinx ; extra == 'develop'
Provides-Extra: test
Requires-Dist: pytest ; extra == 'test'
Requires-Dist: flake8 ; extra == 'test'
Requires-Dist: coverage ; extra == 'test'
Requires-Dist: pep8 ; extra == 'test'
Requires-Dist: tox ; extra == 'test'
